Faizur_URL/Faizur_URL.py
Faizur_URL/__init__.py
Faizur_URL-1.0.dist-info/METADATA
Faizur_URL-1.0.dist-info/WHEEL
Faizur_URL-1.0.dist-info/top_level.txt
Faizur_URL-1.0.dist-info/RECORD
