Metadata-Version: 2.1
Name: Faizur-URL
Version: 1.0
Summary: A Python module for URL shortening with various services BY Faizur
Author: Faizur
Author-email: Faizursearch@gmail.com
Classifier: License :: OSI Approved :: MIT License
Classifier: Programming Language :: Python :: 3
Classifier: Programming Language :: Python :: 3.6
Classifier: Programming Language :: Python :: 3.7
Classifier: Programming Language :: Python :: 3.8
Classifier: Programming Language :: Python :: 3.9
Requires-Dist: pyshorteners
